setup.py
distriprob/Binomialdistribution.py
distriprob/Gaussiandistribution.py
distriprob/Generaldistribution.py
distriprob/__init__.py
distriprob.egg-info/PKG-INFO
distriprob.egg-info/SOURCES.txt
distriprob.egg-info/dependency_links.txt
distriprob.egg-info/not-zip-safe
distriprob.egg-info/top_level.txt